fulgora/__init__.py
fulgora/api.py
fulgora/basis_sets.py
fulgora/cli.py
fulgora/names.py
fulgora/input/arguments.py
fulgora/input/convert.py
fulgora/input/footers.py
fulgora/input/headers.py
fulgora/output/parser.py
fulgora/output/writer.py
fulgora/runners/formchk.py
fulgora/runners/g16.py
fulgora/util/directory.py
fulgora/util/string.py
fulgora/util/units.py
fulgora/visualise/energy.py
fulgora-0.1.0.dist-info/METADATA
fulgora-0.1.0.dist-info/WHEEL
fulgora-0.1.0.dist-info/entry_points.txt
fulgora-0.1.0.dist-info/top_level.txt
fulgora-0.1.0.dist-info/RECORD
