Metadata-Version: 2.1
Name: fulgora
Version: 0.1.0
Summary: A Python package for calculating molecular energy using Gaussian.
Author-email: Jordan Dialpuri <jordan.dialpuri@york.com>
License: LGPLv3
Classifier: Programming Language :: Python :: 3
Classifier: License :: OSI Approved :: GNU Lesser General Public License v3 (LGPLv3)
Classifier: Operating System :: OS Independent
Requires-Python: >=3.7
Requires-Dist: gemmi
Requires-Dist: polars
